extra/color_options_hex.txt
nanomath/__init__.py
nanomath/nanomath.py
nanomath/test_nanomath.py
nanoplot/NanoPlot.py
nanoplot/__init__.py
nanoplot/filteroptions.py
nanoplot/report.py
nanoplot/utils.py
nanoplot/version.py
nanoplot-1.46.2.data/data/LICENSE
nanoplot-1.46.2.dist-info/licenses/LICENSE
nanoplotter/__init__.py
nanoplotter/nanoplotter_main.py
nanoplotter/plot.py
nanoplotter/spatial_heatmap.py
nanoplotter/timeplots.py
scripts/add_barcodes_to_summary.py
scripts/fastq_to_tsv.py
scripts/sequencing_speed_only.py
scripts/split_summary_on_barcodes.py
scripts/test.sh
nanoplot-1.46.2.dist-info/METADATA
nanoplot-1.46.2.dist-info/WHEEL
nanoplot-1.46.2.dist-info/entry_points.txt
nanoplot-1.46.2.dist-info/top_level.txt
nanoplot-1.46.2.dist-info/RECORD
