Metadata-Version: 2.4
Name: nanoplot
Version: 1.46.2
Summary: Plotting suite for Oxford Nanopore sequencing data and alignments
Home-page: https://github.com/wdecoster/NanoPlot
Author: Wouter De Coster
Author-email: decosterwouter@gmail.com
License: MIT
Keywords: nanopore sequencing plotting quality control
Classifier: Development Status :: 4 - Beta
Classifier: Intended Audience :: Science/Research
Classifier: Topic :: Scientific/Engineering :: Bio-Informatics
Classifier: License :: OSI Approved :: MIT License
Classifier: Programming Language :: Python :: 3
Classifier: Programming Language :: Python :: 3.3
Classifier: Programming Language :: Python :: 3.4
Classifier: Programming Language :: Python :: 3.5
Requires-Python: >=3
License-File: LICENSE
Requires-Dist: biopython
Requires-Dist: pysam>0.10.0.0
Requires-Dist: pandas>=1.1.0
Requires-Dist: numpy>=1.16.5
Requires-Dist: scipy
Requires-Dist: python-dateutil
Requires-Dist: nanoget>=1.19.4
Requires-Dist: plotly>=6.1.1
Requires-Dist: pyarrow
Requires-Dist: kaleido>=1.0.0
Dynamic: author
Dynamic: author-email
Dynamic: classifier
Dynamic: description
Dynamic: description-content-type
Dynamic: home-page
Dynamic: keywords
Dynamic: license
Dynamic: license-file
Dynamic: requires-dist
Dynamic: requires-python
Dynamic: summary
